{"_ts":[1475330211],"_r":{"breakdown":{"html":{"bytes":[38166],"requests":[6]},"js":{"bytes":[465611],"requests":[15]},"css":{"bytes":[42602],"requests":[5]},"image":{"bytes":[1382923],"requests":[12]},"flash":{"bytes":[0],"requests":[0]},"font":{"bytes":[68509],"requests":[5]},"other":{"bytes":[0],"requests":[0]}},"date":[1475330211],"domElements":[545],"domInteractive":[1766],"firstPaint":[1814],"fullyLoaded":[5703],"id":["161001_JJ_K3N"],"loadTime":[3373],"render":[1591],"SpeedIndex":[1680],"TTFB":[207],"videoFrames":[[{"_t":0,"_vc":0},{"_t":1600,"_vc":80},{"_t":2000,"_vc":100},{"_t":2600,"_vc":100},{"_t":3600,"_vc":100},{"_t":4500,"_vc":100}]],"visualComplete":[2000]}}